experiment_generator/__init__.py
experiment_generator/base_experiment.py
experiment_generator/common_var.py
experiment_generator/config_updater.py
experiment_generator/experiment_generator.py
experiment_generator/f90nml_updater.py
experiment_generator/main.py
experiment_generator/mom6_input_updater.py
experiment_generator/nuopc_runconfig_updater.py
experiment_generator/nuopc_runseq_updater.py
experiment_generator/om2_forcing_updater.py
experiment_generator/perturbation_experiment.py
experiment_generator/utils.py
experiment_generator/tmp_parser/__init__.py
experiment_generator/tmp_parser/json_parser.py
experiment_generator/tmp_parser/mom6_input.py
experiment_generator/tmp_parser/nuopc_config.py
experiment_generator/tmp_parser/nuopc_seq.py
experiment_generator/tmp_parser/tmp_utils.py
experiment_generator/tmp_parser/yaml_config.py
experiment_generator-0.7.0.dist-info/licenses/LICENSE
experiment_generator-0.7.0.dist-info/METADATA
experiment_generator-0.7.0.dist-info/WHEEL
experiment_generator-0.7.0.dist-info/entry_points.txt
experiment_generator-0.7.0.dist-info/top_level.txt
experiment_generator-0.7.0.dist-info/RECORD
