Metadata-Version: 2.4
Name: experiment-generator
Version: 0.7.0
Summary: A tool to generate and manage parameter sensitivity experiments.
Author-email: Minghang Li <Minghang.Li1@anu.edu.au>
License: Apache-2.0
Project-URL: Homepage, https://github.com/ACCESS-NRI/access-experiment-generator
Keywords: experiment generator,workflow,access,payu
Classifier: License :: OSI Approved :: Apache Software License
Classifier: Operating System :: POSIX :: Linux
Classifier: Programming Language :: Python :: 3
Classifier: Topic :: Utilities
License-File: LICENSE
Requires-Dist: ruamel.yaml
Requires-Dist: f90nml
Requires-Dist: payu
Provides-Extra: devel
Requires-Dist: flake8; extra == "devel"
Requires-Dist: black; extra == "devel"
Requires-Dist: pre-commit; extra == "devel"
Provides-Extra: test
Requires-Dist: pytest; extra == "test"
Requires-Dist: pytest-cov; extra == "test"
Dynamic: license-file
